kanaries_track/__init__.py
kanaries_track/client.py
kanaries_track/config.py
kanaries_track/request.py
kanaries_track-0.0.3.dist-info/METADATA
kanaries_track-0.0.3.dist-info/WHEEL
kanaries_track-0.0.3.dist-info/licenses/LICENSE
kanaries_track-0.0.3.dist-info/RECORD
